<?xml version="1.0" encoding="UTF-8"?>
<!DOCTYPE hibernate-mapping PUBLIC "-//Hibernate/Hibernate Mapping DTD 3.0//EN" "http://hibernate.sourceforge.net/hibernate-mapping-3.0.dtd">
<hibernate-mapping>
  <class name="model.Compra" table="Compra">
    <id column="id" name="id">
      <generator class="increment"/>
    </id>
    <property column="usuario" name="usuario"/>
    <property column="data_da_compra" name="data_da_compra"/>
    
    <set name="itens" lazy="false">
      <key column="id" />
      <one-to-many class="model.Item"/>
    </set>
    
  </class>
</hibernate-mapping>
